data_collators/__init__.py
data_collators/bertnot_collator.py
data_collators/dagn_collator.py
data_collators/fairr_collator.py
data_collators/proofwriter_collator.py
data_collators/prover_collator.py
data_collators/ruletaker_collator.py
datasets/__init__.py
datasets/base.py
datasets/exceptions.py
datasets/utils.py
datasets/mcqa/__init__.py
datasets/mcqa/arlsat_dataset.py
datasets/mcqa/logiqa_dataset.py
datasets/mcqa/reclor_dataset.py
datasets/mlm/__init__.py
datasets/mlm/wiki20k_dataset.py
datasets/proof_qa/__init__.py
datasets/proof_qa/proofwriter_dataset.py
datasets/qa/__init__.py
datasets/qa/abduction_rules_dataset.py
datasets/qa/pararules_plus_dataset.py
datasets/qa/ruletaker_dataset.py
datasets/te/__init__.py
datasets/te/control_dataset.py
datasets/te/mnli_dataset.py
datasets/te/negated_mnli_dataset.py
datasets/te/negated_rte_dataset.py
datasets/te/negated_snli_dataset.py
datasets/te/rte_dataset.py
datasets/te/snli_dataset.py
losses/__init__.py
losses/unlikelihood_loss.py
models/__init__.py
models/adalogn.py
models/bertnot.py
models/dagn.py
models/exceptions.py
models/fairr.py
models/focal_reasoner.py
models/lreasoner.py
models/proofwriter.py
models/prover.py
models/ruletaker.py
pl_models/__init__.py
pl_models/bertnot.py
pl_models/proofwriter.py
pl_models/prover.py
pl_models/ruletaker.py
utilities/__init__.py
utilities/coreference_resolution.py
utilities/discourse_delimiter.py
utilities/exceptions.py
utilities/extract_logical_expressions.py
utilities/sentiment_analysis.py
utilities/triplets_extraction.py
logitorch-0.0.0.dist-info/LICENSE
logitorch-0.0.0.dist-info/METADATA
logitorch-0.0.0.dist-info/WHEEL
logitorch-0.0.0.dist-info/top_level.txt
logitorch-0.0.0.dist-info/RECORD
