Metadata-Version: 2.1
Name: logitorch
Version: 0.0.0
Summary: LogiTorch is a pytorch-based library for logical reasoning in natural language
Home-page: https://github.com/ChadiHelwe/logitorch
Author: Chadi Helwe
Author-email: chadi.helwe@gmail.com
License: Apache License 2.0
Classifier: Programming Language :: Python :: 3
Classifier: Programming Language :: Python :: 3.8
Classifier: Programming Language :: Python :: 3.9
Classifier: Programming Language :: Python :: 3.10
License-File: LICENSE
Requires-Dist: torch (~=1.8.0)
Requires-Dist: pytorch-lightning (~=1.6.0)
Requires-Dist: transformers (~=4.21.0)
Requires-Dist: allennlp (~=2.8.0)
Requires-Dist: allennlp-models (~=2.8.0)
Requires-Dist: requests (~=2.27.0)
Requires-Dist: tqdm (~=4.64.0)
Requires-Dist: textblob (~=0.17.0)
Requires-Dist: nltk (~=3.7.0)
Provides-Extra: dev
Requires-Dist: tox (~=3.25.0) ; extra == 'dev'
Requires-Dist: isort (~=5.9.0) ; extra == 'dev'
Requires-Dist: mypy (~=1.2.0) ; extra == 'dev'
Requires-Dist: black (~=19.0) ; extra == 'dev'
Requires-Dist: pytest (~=7.1.0) ; extra == 'dev'
Requires-Dist: flake8 (~=3.9.0) ; extra == 'dev'
Requires-Dist: pre-commit (~=2.20.0) ; extra == 'dev'
Requires-Dist: types-requests (~=2.28.0) ; extra == 'dev'
Requires-Dist: sphinx (~=4.4.0) ; extra == 'dev'
Requires-Dist: sphinx-autoapi (~=1.8.0) ; extra == 'dev'
Requires-Dist: furo (~=2022.6.0) ; extra == 'dev'
